mocr/__init__.py
mocr/__main__.py
mocr/face_detection.py
mocr/text_recognition.py
mocr/haarcascades/haarcascade_frontalface_default.xml
mocr-0.4.0.dist-info/COPYING
mocr-0.4.0.dist-info/LICENSE
mocr-0.4.0.dist-info/METADATA
mocr-0.4.0.dist-info/NOTICE
mocr-0.4.0.dist-info/WHEEL
mocr-0.4.0.dist-info/top_level.txt
mocr-0.4.0.dist-info/RECORD
