Metadata-Version: 2.1
Name: mocr
Version: 0.4.0
Summary: Meaningful Optical Character Recognition from identity cards with Deep Learning.
Home-page: https://github.com/verifid/mocr
Author: Abdullah Selek
Author-email: abdullahselek@gmail.com
Maintainer: Abdullah Selek
Maintainer-email: abdullahselek@gmail.com
License: MIT License
Download-URL: https://pypi.org/project/mocr/
Keywords: ocr,optical character recognition,identity card,deep learning,opencv,meaningful
Platform: Any
Classifier: Intended Audience :: Developers
Classifier: License :: OSI Approved :: MIT License
Classifier: Operating System :: OS Independent
Classifier: Topic :: Software Development :: Libraries :: Python Modules
Classifier: Programming Language :: Python
Classifier: Programming Language :: Python :: 3.6
Classifier: Programming Language :: Python :: 3.7
Classifier: Programming Language :: Python :: 3.8
Requires-Dist: opencv-python (>=4.4.0)
Requires-Dist: opencv-contrib-python (>=4.4.0)
Requires-Dist: pillow (>=8.0.0)
Requires-Dist: pytesseract (>=0.3.6)
Requires-Dist: imutils (>=0.5.3)
Requires-Dist: numpy (>=1.19.2)
